wetteronline/__init__.py
wetteronline/api.py
wetteronline-0.0.3.dist-info/LICENSE
wetteronline-0.0.3.dist-info/METADATA
wetteronline-0.0.3.dist-info/WHEEL
wetteronline-0.0.3.dist-info/top_level.txt
wetteronline-0.0.3.dist-info/RECORD
